CHANGES.txt
INSTALL.txt
bootstrap.py
buildout.cfg
setup.py
skels/instance/site.zcml
src/ldappas/README.txt
src/ldappas/SETUP.cfg
src/ldappas/TODO.txt
src/ldappas/__init__.py
src/ldappas/authentication.py
src/ldappas/configure.zcml
src/ldappas/i18n.py
src/ldappas/interfaces.py
src/ldappas/ldappas-configure.zcml
src/ldappas/tests.py
src/ldappas.egg-info/PKG-INFO
src/ldappas.egg-info/SOURCES.txt
src/ldappas.egg-info/dependency_links.txt
src/ldappas.egg-info/not-zip-safe
src/ldappas.egg-info/requires.txt
src/ldappas.egg-info/top_level.txt