Metadata-Version: 1.0
Name: ldappas
Version: 0.8.3
Summary: LDAP-based authenticator for Zope 3. It uses ldapadapter to talk to an
